{
  "ut_updated": 1705795376,
  "time_updated": "2024-01-21 05:32:56",
  "store_id": "cargillslk",
  "sku_code": "CSE0356",
  "category_code": "CE",
  "name": "Finch Basil Leaves",
  "short_description": "Dried Basil Leaves",
  "description": "Use this top-notch basil to add some finishing flair to your ratatouille, vegetarian chili, or any\ntomato-based meal. Basil works beautifully with thyme, tarragon, anise, cloves, cinnamon, and other spices as well as\nlemon and lime. Basil tea is also highly delicious *Images for illustration purposes only. Product received may vary.",
  "unit_of_measure": "g",
  "unit_size": 20.0,
  "price_of_unit": 490.0
}