{
  "ut_updated": 1703814996,
  "time_updated": "2023-12-29 07:26:36",
  "store_id": "cargillslk",
  "sku_code": "SC10378",
  "category_code": "SC",
  "name": "Maliban Custard Cream Biscuits",
  "short_description": "Biscuits",
  "description": "The creaminess of the custard cream enclosed within two custard flavoured cookies makes you yearning and longing for more. *Images for illustration purposes only. Product received may vary.",
  "unit_of_measure": "g",
  "unit_size": 410.0,
  "price_of_unit": 420.0
}