{
  "ut_updated": 1706832162,
  "time_updated": "2024-02-02 05:32:42",
  "store_id": "cargillslk",
  "sku_code": "PCE0855",
  "category_code": "HB",
  "name": "Signal Kids Toothpaste, Orange",
  "short_description": "Kids Toothpaste",
  "description": "Signal Kids Toothpaste contains a Mild & gentle formula that protects little teeth from acid attacks that lead to cavities and strengthens enamel. Available in orange flavor kids will love. *Images for illustration purpose only, Product recieved may vary.",
  "unit_of_measure": "g",
  "unit_size": 40.0,
  "price_of_unit": 160.0
}