{
  "ut_updated": 1705104169,
  "time_updated": "2024-01-13 05:32:49",
  "store_id": "cargillslk",
  "sku_code": "CS30116",
  "category_code": "FC",
  "name": "MD Date & Lime Chutney",
  "short_description": "Date & Lime Chutney",
  "description": "MD Date & Lime Chutney is made  out of fresh and natural vegetables, and no artificial colours or preservatives added . *Images for illustration purpose only. Products received may vary.",
  "unit_of_measure": "g",
  "unit_size": 450.0,
  "price_of_unit": 890.0
}