{
  "ut_updated": 1703135356,
  "time_updated": "2023-12-21 10:39:16",
  "store_id": "cargillslk",
  "sku_code": "BV05004",
  "name": "Milca Instant Milk Powder",
  "short_description": "Full Cream Milk Powder",
  "description": "Milca Full Cream Milk Powder is easily soluble and is made from high qulaity fresh milk extracted from the finest dairy cows of New Zealand. *Images for illustration purposes only. Product received may vary.",
  "unit_of_measure": "g",
  "unit_size": 400.0,
  "category_code": "DY"
}