{
  "ut_updated": 1705104169,
  "time_updated": "2024-01-13 05:32:49",
  "store_id": "cargillslk",
  "sku_code": "DI70103",
  "category_code": "DI",
  "name": "Seven Star Cake Flour",
  "short_description": "Cake Flour",
  "description": "Made from a special soft wheat, 7 star cake flour is intended for the preparation of the finest cakes, cookies, muffins and sweet treats. This makes cakes softer & tastier! *Images for illustration purposes only. Product received may vary.",
  "unit_of_measure": "kg",
  "unit_size": 1.0,
  "price_of_unit": 280.0
}