{
  "ut_updated": 1703135356,
  "time_updated": "2023-12-21 10:39:16",
  "store_id": "cargillslk",
  "sku_code": "DY10114",
  "name": "Lurpak Butter Slightly Salted",
  "short_description": "Butter",
  "description": "Lurpak salted butter is made with fresh cream and a sprinkling of salt. Lurpak slightly salted butter has a legendary subtlety and freshness. It is perfect to mix, fry, drizzle and bake into all kinds of creations. Please note that our team at Cargills Online has taken all the necessary precausions in order to deliver this item in its frozen state to your doorstep. *Images for illustration purposes only. Product received may vary.",
  "unit_of_measure": "g",
  "unit_size": 250.0,
  "category_code": "DY"
}