{
  "ut_updated": 1704844965,
  "time_updated": "2024-01-10 05:32:45",
  "store_id": "cargillslk",
  "sku_code": "PCE0478",
  "category_code": "HB",
  "name": "Chandanalepa Powdered Face Wash Sandalwood",
  "short_description": "Face Wash",
  "description": "Chandanalepa Sandalwood Face Wash Powder combining the herbal ayurvedic properties of sandalwood, Cosciniumfenestratum (commonly known as venivel), turmeric, kokum flakes and Welmi. Chandanalepa Herbal Face wash Powder, does not contain any sulphates.",
  "unit_of_measure": "g",
  "unit_size": 30.0,
  "price_of_unit": 408.0
}