{
  "ut_updated": 1705104169,
  "time_updated": "2024-01-13 05:32:49",
  "store_id": "cargillslk",
  "sku_code": "DYD0305",
  "category_code": "DY",
  "name": "Kotmale Non Fat Yoghurt",
  "short_description": "Non Fat Yoghurt",
  "description": "Kotmale Non fat Yoghurt is an unsweetened yoghurt without fat, made from 100% Sri Lankan Fresh Cow's Milk. Suitable for Vegetarians. Rs. 50 cents from every 1L of fresh milk collected is contributed to a special welfare fund \"Sarubima\" focused on empowering Farmers children through education.      *Images for illustration purposes only. Product received may vary.",
  "unit_of_measure": "g",
  "unit_size": 450.0,
  "price_of_unit": 370.0
}